python_proto_importer-0.1.4.dist-info/METADATA
python_proto_importer-0.1.4.dist-info/WHEEL
python_proto_importer-0.1.4.dist-info/entry_points.txt
python_proto_importer-0.1.4.dist-info/licenses/LICENSE
python_proto_importer/__init__.py
python_proto_importer/python_proto_importer.abi3.so
python_proto_importer-0.1.4.dist-info/RECORD
