Metadata-Version: 2.4
Name: python-proto-importer
Version: 0.1.4
Classifier: Programming Language :: Python
Classifier: Programming Language :: Rust
Classifier: License :: OSI Approved :: Apache Software License
Classifier: Operating System :: OS Independent
Classifier: Programming Language :: Python :: 3
Classifier: Programming Language :: Python :: 3 :: Only
Classifier: Programming Language :: Python :: 3.11
Classifier: Programming Language :: Python :: 3.12
Classifier: Programming Language :: Python :: 3.13
Classifier: Operating System :: POSIX :: Linux
Classifier: Operating System :: MacOS :: MacOS X
Classifier: Operating System :: Microsoft :: Windows
Requires-Dist: maturin>=1.4,<2
License-File: LICENSE
Summary: Rust-based CLI to streamline Python gRPC/Protobuf workflows
Keywords: protobuf,grpc,python,generator,cli
Home-Page: https://github.com/K-dash/python-proto-importer
Author-email: K-dash <maintainers+python-proto-importer@kdash.dev>
License: Apache-2.0
Requires-Python: >=3.11
Project-URL: Homepage, https://github.com/K-dash/python-proto-importer
Project-URL: Repository, https://github.com/K-dash/python-proto-importer
